CentralizedClient/CentralizedLLMClient.py
CentralizedClient/__init__.py
CentralizedClient/file_processor.py
CentralizedClient/gemini_provider.py
CentralizedClient/key_manager.py
CentralizedClient/llm_logger.py
CentralizedClient/openai_provider.py
CentralizedClient/openrouter_provider.py
CentralizedClient/test.py
CentralizedClient/utils/__init__.py
CentralizedClient/utils/atlas_client.py
CentralizedClient/utils/s3_file_manager.py
centralized_llm_client-0.1.1.dist-info/licenses/LICENSE
centralized_llm_client-0.1.1.dist-info/METADATA
centralized_llm_client-0.1.1.dist-info/WHEEL
centralized_llm_client-0.1.1.dist-info/top_level.txt
centralized_llm_client-0.1.1.dist-info/RECORD
