Metadata-Version: 2.4
Name: centralized-llm-client
Version: 0.1.1
Summary: Unified Python client for multiple LLM providers with fallback, file handling, and logging.
Author-email: Hrithik <hrithik@qusandbox.com>
License: MIT License
Classifier: Programming Language :: Python :: 3
Classifier: Operating System :: OS Independent
Classifier: License :: OSI Approved :: MIT License
Classifier: Intended Audience :: Developers
Classifier: Topic :: Software Development :: Libraries :: Python Modules
Requires-Python: >=3.9
License-File: LICENSE
Requires-Dist: openai
Requires-Dist: google-generativeai
Requires-Dist: boto3
Requires-Dist: python-dotenv
Requires-Dist: fastapi
Requires-Dist: pymongo
Requires-Dist: cryptography
Requires-Dist: starlette
Dynamic: license-file
